setup.py
Axe.egg-info/PKG-INFO
Axe.egg-info/SOURCES.txt
Axe.egg-info/dependency_links.txt
Axe.egg-info/top_level.txt
axe/__init__.py
axe/app.py
axe/default_exts.py
axe/errors.py
axe/http_exceptions.py
tests/suites/__init__.py
tests/suites/default_ext.py
tests/suites/hello.py
tests/suites/pshell.py