Metadata-Version: 1.1
Name: Axe
Version: 0.0.4
Summary: An Extendable Python Web Framework
Home-page: https://github.com/soasme/axe
Author: Ju Lin
Author-email: soasme@gmail.com
License: MIT License
Keywords: Web frameword
Platform: UNKNOWN
Classifier: Development Status :: 4 - Beta
Classifier: Environment :: Web Environment
Classifier: Intended Audience :: Developers
Classifier: Operating System :: OS Independent
Classifier: Programming Language :: Python
Classifier: Programming Language :: Python :: 3
Classifier: License :: OSI Approved :: MIT License
Classifier: Topic :: Internet :: WWW/HTTP :: Dynamic Content
Classifier: Topic :: Software Development :: Libraries :: Python Modules
